my_lib_e859f2/__about__.py
my_lib_e859f2/__init__.py
my_lib_e859f2-0.0.1.dist-info/METADATA
my_lib_e859f2-0.0.1.dist-info/WHEEL
my_lib_e859f2-0.0.1.dist-info/licenses/LICENSE.txt
my_lib_e859f2-0.0.1.dist-info/RECORD
