Metadata-Version: 2.4
Name: my-lib-e859f2
Version: 0.0.1
Project-URL: Documentation, https://github.com/Adrian Herscu/my-hatch-project#readme
Project-URL: Issues, https://github.com/Adrian Herscu/my-hatch-project/issues
Project-URL: Source, https://github.com/Adrian Herscu/my-hatch-project
Author-email: Adrian Herscu <adrian.herscu@gmail.com>
License-Expression: MIT
License-File: LICENSE.txt
Classifier: Development Status :: 4 - Beta
Classifier: Programming Language :: Python
Classifier: Programming Language :: Python :: 3.8
Classifier: Programming Language :: Python :: 3.9
Classifier: Programming Language :: Python :: 3.10
Classifier: Programming Language :: Python :: 3.11
Classifier: Programming Language :: Python :: 3.12
Classifier: Programming Language :: Python :: Implementation :: CPython
Classifier: Programming Language :: Python :: Implementation :: PyPy
Requires-Python: >=3.8
Requires-Dist: requests
